api_tester/__init__.py
api_tester/auth.py
api_tester/cli.py
api_tester/client.py
api_tester/factory.py
restquest-1.2.2.dist-info/METADATA
restquest-1.2.2.dist-info/WHEEL
restquest-1.2.2.dist-info/entry_points.txt
restquest-1.2.2.dist-info/top_level.txt
restquest-1.2.2.dist-info/RECORD
