Metadata-Version: 2.2
Name: restquest
Version: 1.2.2
Summary: A Python package to test API endpoints easily
Home-page: https://github.com/Moataz0000/api_tester
Author: Moataz Fawzy
Author-email: your-email@example.com
Classifier: Programming Language :: Python :: 3
Classifier: License :: OSI Approved :: MIT License
Classifier: Operating System :: OS Independent
Requires-Python: >=3.6
Requires-Dist: requests
Dynamic: author
Dynamic: author-email
Dynamic: classifier
Dynamic: description
Dynamic: description-content-type
Dynamic: home-page
Dynamic: requires-dist
Dynamic: requires-python
Dynamic: summary
